FreeStrange/__init__.py
FreeStrange/Operater/__init__.py
FreeStrange/Port/__init__.py
FreeStrange/ScriptEngine/__init__.py
FreeStrange-1.0.3.data/scripts/entry.py
FreeStrange-1.0.3.dist-info/LICENSE
FreeStrange-1.0.3.dist-info/METADATA
FreeStrange-1.0.3.dist-info/WHEEL
FreeStrange-1.0.3.dist-info/top_level.txt
FreeStrange-1.0.3.dist-info/zip-safe
FreeStrange-1.0.3.dist-info/RECORD
