Metadata-Version: 2.1
Name: FreeStrange
Version: 1.0.3
Summary: A unlock data system
Home-page: https://github.com/CleverCreater/FreeData
Author: CleverCreator
Author-email: clevercreator@10minutesmail.com
License: MIT
Platform: Linux
Platform: MacOS
Requires-Python: >=3.9
